{
  "name": "nomilous.io",
  "repo": "nomilous/nomilous.io",
  "description": "homepage",
  "version": "0.0.0",
  "keywords": [],
  "dependencies": {
    "then/promise": "*",
    "matthewp/xhr": "*",
    "component/dom": "*",
    "nomilous/three-webgl-renderer": "0.0.1",
    "nomilous/three-camera": "0.0.1",
    "nomilous/three-scene": "0.0.1",
    "nomilous/three-line": "0.0.1",
    "nomilous/three-particle": "0.0.1",
    "nomilous/three-stats": "*",
    "nomilous/three": "0.0.1"
  },
  "development": {},
  "license": "MIT",
  "scripts": [],
  "remotes": []
}